django_simple_tags/__init__.py
django_simple_tags/admin.py
django_simple_tags/apps.py
django_simple_tags/models.py
django_simple_tags/tests.py
django_simple_tags/utils.py
django_simple_tags/views.py
django_simple_tags/migrations/__init__.py
django_simple_tags/templatetags/__init__.py
django_simple_tags/templatetags/django_simple_tags.py
django_simple_tags-0.6.2.dist-info/licenses/LICENSE
django_simple_tags-0.6.2.dist-info/METADATA
django_simple_tags-0.6.2.dist-info/WHEEL
django_simple_tags-0.6.2.dist-info/top_level.txt
django_simple_tags-0.6.2.dist-info/RECORD
